graphviz2drawio/__init__.py
graphviz2drawio/__main__.py
graphviz2drawio/graphviz2drawio.py
graphviz2drawio/py.typed
graphviz2drawio/version.py
graphviz2drawio/models/Arguments.py
graphviz2drawio/models/CoordsTranslate.py
graphviz2drawio/models/DotAttr.py
graphviz2drawio/models/Errors.py
graphviz2drawio/models/Rect.py
graphviz2drawio/models/SVG.py
graphviz2drawio/models/SvgParser.py
graphviz2drawio/models/__init__.py
graphviz2drawio/models/commented_tree_builder.py
graphviz2drawio/mx/Curve.py
graphviz2drawio/mx/CurveFactory.py
graphviz2drawio/mx/Edge.py
graphviz2drawio/mx/EdgeFactory.py
graphviz2drawio/mx/GraphObj.py
graphviz2drawio/mx/MxConst.py
graphviz2drawio/mx/MxGraph.py
graphviz2drawio/mx/Node.py
graphviz2drawio/mx/NodeFactory.py
graphviz2drawio/mx/RectFactory.py
graphviz2drawio/mx/Shape.py
graphviz2drawio/mx/Styles.py
graphviz2drawio/mx/Text.py
graphviz2drawio/mx/__init__.py
graphviz2drawio/mx/bezier.py
graphviz2drawio/mx/image.py
graphviz2drawio/mx/utils.py
graphviz2drawio-1.0.0.dist-info/LICENSE.md
graphviz2drawio-1.0.0.dist-info/METADATA
graphviz2drawio-1.0.0.dist-info/WHEEL
graphviz2drawio-1.0.0.dist-info/entry_points.txt
graphviz2drawio-1.0.0.dist-info/top_level.txt
graphviz2drawio-1.0.0.dist-info/RECORD
