Metadata-Version: 2.1
Name: graphviz2drawio
Version: 1.0.0
Summary: Convert graphviz (dot) files to draw.io / lucid (mxGraph) format. Beautiful and editable graphs in your favorite editor.
Home-page: https://github.com/hbmartin/graphviz2drawio/
Author: Harold Martin
Author-email: harold.martin@gmail.com
License: GPLv3
Project-URL: Bug Reports, https://github.com/hbmartin/graphviz2drawio/issues
Project-URL: Source, https://github.com/hbmartin/graphviz2drawio/
Keywords: graphviz graph agraph dot convert conversion draw drawio mxgraph maxgraph
Classifier: Development Status :: 5 - Production/Stable
Classifier: Intended Audience :: Developers
Classifier: Intended Audience :: End Users/Desktop
Classifier: Intended Audience :: Information Technology
Classifier: Intended Audience :: Science/Research
Classifier: Topic :: Multimedia :: Graphics
Classifier: Topic :: Multimedia :: Graphics :: Graphics Conversion
Classifier: Topic :: Scientific/Engineering :: Visualization
Classifier: Topic :: Scientific/Engineering :: Visualization
Classifier: License :: OSI Approved :: GNU General Public License v3 or later (GPLv3+)
Classifier: Programming Language :: Python :: 3
Classifier: Programming Language :: Python :: 3.10
Classifier: Programming Language :: Python :: 3.11
Classifier: Programming Language :: Python :: 3.12
Classifier: Programming Language :: Python :: 3.13
Requires-Python: >=3.10
License-File: LICENSE.md
Requires-Dist: puremagic
Requires-Dist: pygraphviz
Requires-Dist: svg.path
